agentsmgr/data/.gitignore
agentsmgr/data/configuration/general.toml
agentsmgr/__init__.py
agentsmgr/__main__.py
agentsmgr/cli.py
agentsmgr/cmdbase.py
agentsmgr/context.py
agentsmgr/core.py
agentsmgr/detection.py
agentsmgr/exceptions.py
agentsmgr/generator.py
agentsmgr/instructions.py
agentsmgr/memorylinks.py
agentsmgr/nomina.py
agentsmgr/operations.py
agentsmgr/population.py
agentsmgr/py.typed
agentsmgr/results.py
agentsmgr/userdata.py
agentsmgr/__/__init__.py
agentsmgr/__/imports.py
agentsmgr/__/nomina.py
agentsmgr/_typedecls/dulwich/__init__.pyi
agentsmgr/_typedecls/dulwich/porcelain.pyi
agentsmgr/_typedecls/dulwich/repo.pyi
agentsmgr/maintenance/__.py
agentsmgr/maintenance/__init__.py
agentsmgr/maintenance/__main__.py
agentsmgr/maintenance/cli.py
agentsmgr/maintenance/validation.py
agentsmgr/renderers/__.py
agentsmgr/renderers/__init__.py
agentsmgr/renderers/base.py
agentsmgr/renderers/claude.py
agentsmgr/renderers/codex.py
agentsmgr/renderers/gemini.py
agentsmgr/renderers/opencode.py
agentsmgr/renderers/qwen.py
agentsmgr/sources/__.py
agentsmgr/sources/__init__.py
agentsmgr/sources/base.py
agentsmgr/sources/git.py
agentsmgr/sources/local.py
emcd_agents-1.0a3.dist-info/METADATA
emcd_agents-1.0a3.dist-info/WHEEL
emcd_agents-1.0a3.dist-info/entry_points.txt
emcd_agents-1.0a3.dist-info/licenses/LICENSE.txt
emcd_agents-1.0a3.dist-info/RECORD
